browz/AboutBrowzDialog.py
browz/BrowzWindow.py
browz/PreferencesBrowzDialog.py
browz/__init__.py
browz_lib/AboutDialog.py
browz_lib/Builder.py
browz_lib/PreferencesDialog.py
browz_lib/Window.py
browz_lib/__init__.py
browz_lib/browzconfig.py
browz_lib/helpers.py
browz-1.0.1.dist-info/AUTHORS
browz-1.0.1.dist-info/METADATA
browz-1.0.1.dist-info/WHEEL
browz-1.0.1.dist-info/top_level.txt
browz-1.0.1.dist-info/RECORD
